cgt_py-0.5.0.dist-info/METADATA
cgt_py-0.5.0.dist-info/WHEEL
cgt_py/__init__.py
cgt_py/cgt_py.cp310-win32.pyd
cgt_py-0.5.0.dist-info/RECORD
